dynesty/__init__.py
dynesty/_version.py
dynesty/bounding.py
dynesty/dynamicsampler.py
dynesty/dynesty.py
dynesty/nestedsamplers.py
dynesty/plotting.py
dynesty/pool.py
dynesty/results.py
dynesty/sampler.py
dynesty/sampling.py
dynesty/utils.py
dynesty-2.1.4.dist-info/AUTHORS.md
dynesty-2.1.4.dist-info/LICENSE
dynesty-2.1.4.dist-info/METADATA
dynesty-2.1.4.dist-info/WHEEL
dynesty-2.1.4.dist-info/top_level.txt
dynesty-2.1.4.dist-info/RECORD
