Metadata-Version: 2.1
Name: dynesty
Version: 2.1.4
Summary: A dynamic nested sampling package for computing Bayesian posteriors and evidences.
Home-page: https://github.com/joshspeagle/dynesty
Author: Joshua S Speagle, Sergey E Koposov
Author-email: j.speagle@utoronto.ca
License: MIT
Keywords: nested sampling,dynamic,monte carlo,bayesian,inference,modeling
Classifier: Development Status :: 5 - Production/Stable
Classifier: License :: OSI Approved :: MIT License
Classifier: Natural Language :: English
Classifier: Programming Language :: Python
Classifier: Operating System :: OS Independent
Classifier: Topic :: Scientific/Engineering
Classifier: Intended Audience :: Science/Research
License-File: LICENSE
License-File: AUTHORS.md
